emailsec/__init__.py
emailsec/_alignment.py
emailsec/_authentication_results.py
emailsec/_dns_resolver.py
emailsec/_errors.py
emailsec/_utils.py
emailsec/arc.py
emailsec/auth.py
emailsec/config.py
emailsec/dmarc.py
emailsec/dnsbl.py
emailsec/py.typed
emailsec/dkim/__init__.py
emailsec/dkim/checker.py
emailsec/dkim/parser.py
emailsec/spf/__init__.py
emailsec/spf/checker.py
emailsec/spf/expander.py
emailsec/spf/parser.py
emailsec-0.6.3.dist-info/METADATA
emailsec-0.6.3.dist-info/WHEEL
emailsec-0.6.3.dist-info/licenses/LICENSE
emailsec-0.6.3.dist-info/RECORD
