Metadata-Version: 2.4
Name: emailsec
Version: 0.6.3
Summary: Authenticate incoming emails with SPF, DKIM, DMARC, and ARC.
Project-URL: Homepage, https://emailsec.hexa.ninja
Project-URL: Documentation, https://emailsec.hexa.ninja
Project-URL: Repository, https://git.sr.ht/~tsileo/emailsec
Author-email: Thomas Sileo <thomas.sileo@sent.com>
License-Expression: MIT
License-File: LICENSE
Classifier: Development Status :: 3 - Alpha
Classifier: License :: OSI Approved :: MIT License
Classifier: Programming Language :: Python :: 3
Classifier: Programming Language :: Python :: 3.12
Classifier: Programming Language :: Python :: 3.13
Classifier: Topic :: Communications :: Email
Classifier: Typing :: Typed
Requires-Python: >=3.12
Requires-Dist: aiodns>=3.2.0
Requires-Dist: cachetools>=6.2.0
Requires-Dist: cryptography>=44.0.2
Requires-Dist: publicsuffixlist>=1.0.2.20250428
Requires-Dist: pyparsing>=3.2.3
